tmc_export/__init__.py
tmc_export/py.typed
tmc_export/app/main.py
tmc_export-0.0.7.dist-info/METADATA
tmc_export-0.0.7.dist-info/WHEEL
tmc_export-0.0.7.dist-info/entry_points.txt
tmc_export-0.0.7.dist-info/RECORD
