Metadata-Version: 2.4
Name: tmc-export
Version: 0.0.7
Summary: Utility to run tmc2fcs generator with batteries included
Author-email: Sylvain Guieu <Sylvain.Guieu@gmail.com>
Requires-Python: >=3.11
Requires-Dist: packaging>=25.0
Requires-Dist: pyyaml>=6.0.2
Requires-Dist: requests>=2.32.4
Requires-Dist: rich>=14.0.0
Requires-Dist: typing-extensions>=4.14.1
